scrapytest/__init__.py
scrapytest/cli.py
scrapytest/default_settings.py
scrapytest/exceptions.py
scrapytest/notifiers.py
scrapytest/runner.py
scrapytest/spec.py
scrapytest/tests.py
scrapytest/utils.py
scrapytest/validate.py
scrapy_test-0.6.1.dist-info/LICENSE
scrapy_test-0.6.1.dist-info/METADATA
scrapy_test-0.6.1.dist-info/WHEEL
scrapy_test-0.6.1.dist-info/entry_points.txt
scrapy_test-0.6.1.dist-info/top_level.txt
scrapy_test-0.6.1.dist-info/RECORD
