Metadata-Version: 2.1
Name: scrapy-test
Version: 0.6.1
Summary: scrapy output testing framework
Home-page: https://gitlab.com/granitosaurus/scrapy-test
Author: granitosaurus
Author-email: granitosaurus@pm.me
License: GPLv3
Platform: UNKNOWN
Requires-Dist: click
Requires-Dist: scrapy
